sabapy/__init__.py
sabapy-0.0.0.dist-info/METADATA
sabapy-0.0.0.dist-info/WHEEL
sabapy-0.0.0.dist-info/top_level.txt
sabapy-0.0.0.dist-info/RECORD
