Metadata-Version: 2.1
Name: sabapy
Version: 0.0.0
Summary: Misc functions used during my work
Home-page: UNKNOWN
Author: Nikolay Dudaev
Author-email: nikolay.dudaev@icloud.com
License: MIT
Platform: UNKNOWN
Requires-Dist: numpy
Requires-Dist: pandas
